ReWord/__init__.py
ReWord/configuration.py
ReWord/dataloader.py
ReWord/model.py
ReWord/pl_wrapper.py
ReWord-0.1.0.dist-info/METADATA
ReWord-0.1.0.dist-info/WHEEL
ReWord-0.1.0.dist-info/top_level.txt
ReWord-0.1.0.dist-info/RECORD
