Metadata-Version: 2.1
Name: ReWord
Version: 0.1.0
Summary: Reorder word in English sentence to follow correct grammar
Author: Le Minh Khoi
License: MIT
Platform: UNKNOWN
Classifier: Programming Language :: Python :: 3
Classifier: License :: OSI Approved :: MIT License
Classifier: Operating System :: OS Independent
Requires-Python: >=3.8
Requires-Dist: torch
Requires-Dist: pytorch-lightning
Requires-Dist: wandb
Requires-Dist: transformers
Requires-Dist: datasets
Requires-Dist: tokenizers
Requires-Dist: sacrebleu
Requires-Dist: sacremoses
